visie/__init__.py
visie/__main__.py
visie/parser.py
visie/variants.py
visie/visie.py
visie-0.1.1.dist-info/LICENSE
visie-0.1.1.dist-info/METADATA
visie-0.1.1.dist-info/WHEEL
visie-0.1.1.dist-info/entry_points.txt
visie-0.1.1.dist-info/top_level.txt
visie-0.1.1.dist-info/RECORD
